wg_utilities/__init__.py
wg_utilities/api/__init__.py
wg_utilities/api/temp_auth_server.py
wg_utilities/clients/__init__.py
wg_utilities/clients/_google.py
wg_utilities/clients/_spotify_types.py
wg_utilities/clients/google_calendar.py
wg_utilities/clients/google_drive.py
wg_utilities/clients/google_fit.py
wg_utilities/clients/google_photos.py
wg_utilities/clients/json_api_client.py
wg_utilities/clients/monzo.py
wg_utilities/clients/oauth_client.py
wg_utilities/clients/spotify.py
wg_utilities/clients/truelayer.py
wg_utilities/decorators/__init__.py
wg_utilities/decorators/process_exception.py
wg_utilities/devices/__init__.py
wg_utilities/devices/dht22/__init__.py
wg_utilities/devices/dht22/dht22_lib.py
wg_utilities/devices/epd/__init__.py
wg_utilities/devices/epd/epd7in5_v2.py
wg_utilities/devices/epd/epdconfig.py
wg_utilities/devices/yamaha_yas_209/__init__.py
wg_utilities/devices/yamaha_yas_209/yamaha_yas_209.py
wg_utilities/exceptions/__init__.py
wg_utilities/exceptions/_deprecated.py
wg_utilities/exceptions/_exception.py
wg_utilities/functions/__init__.py
wg_utilities/functions/_functions.py
wg_utilities/functions/datetime_helpers.py
wg_utilities/functions/decorators.py
wg_utilities/functions/file_management.py
wg_utilities/functions/json.py
wg_utilities/functions/processes.py
wg_utilities/functions/string_manipulation.py
wg_utilities/functions/subclasses.py
wg_utilities/functions/xml.py
wg_utilities/helpers/__init__.py
wg_utilities/helpers/meta/__init__.py
wg_utilities/helpers/meta/post_init.py
wg_utilities/helpers/mixin/__init__.py
wg_utilities/helpers/mixin/instance_cache.py
wg_utilities/helpers/processor/__init__.py
wg_utilities/helpers/processor/json.py
wg_utilities/loggers/__init__.py
wg_utilities/loggers/file_handler.py
wg_utilities/loggers/item_warehouse/__init__.py
wg_utilities/loggers/item_warehouse/base_handler.py
wg_utilities/loggers/item_warehouse/flushable_queue_listener.py
wg_utilities/loggers/item_warehouse/warehouse_handler.py
wg_utilities-5.17.4.dist-info/LICENSE
wg_utilities-5.17.4.dist-info/METADATA
wg_utilities-5.17.4.dist-info/WHEEL
wg_utilities-5.17.4.dist-info/RECORD
