Metadata-Version: 2.3
Name: wg-utilities
Version: 5.17.4
Summary: Loads of useful stuff for the things I do :)
License: MIT
Author: Will Garside
Author-email: worgarside@gmail.com
Maintainer: Will Garside
Maintainer-email: worgarside@gmail.com
Requires-Python: >=3.11
Classifier: License :: OSI Approved :: MIT License
Classifier: Programming Language :: Python :: 3
Classifier: Programming Language :: Python :: 3.11
Classifier: Programming Language :: Python :: 3.12
Classifier: Programming Language :: Python :: 3.13
Provides-Extra: clients
Provides-Extra: devices-dht22
Provides-Extra: devices-epd
Provides-Extra: devices-yamaha-yas-209
Provides-Extra: exceptions
Provides-Extra: functions
Provides-Extra: loggers
Provides-Extra: logging
Provides-Extra: mqtt
Provides-Extra: testing
Requires-Dist: Pillow ; extra == "devices-epd"
Requires-Dist: async-upnp-client ; extra == "devices-yamaha-yas-209"
Requires-Dist: botocore ; extra == "testing"
Requires-Dist: flask ; extra == "clients"
Requires-Dist: lxml ; extra == "functions"
Requires-Dist: paho-mqtt ; extra == "mqtt"
Requires-Dist: pigpio ; extra == "devices-dht22"
Requires-Dist: pydantic (>=2.9.0,<3.0.0)
Requires-Dist: pydantic ; extra == "clients"
Requires-Dist: pydantic ; extra == "devices-yamaha-yas-209"
Requires-Dist: pyjwt ; extra == "clients"
Requires-Dist: requests ; extra == "clients"
Requires-Dist: requests ; extra == "exceptions"
Requires-Dist: requests ; extra == "loggers"
Requires-Dist: requests ; extra == "logging"
Requires-Dist: rpi.gpio ; extra == "devices-epd"
Requires-Dist: spidev ; extra == "devices-epd"
Requires-Dist: tzlocal ; extra == "clients"
Requires-Dist: xmltodict ; extra == "devices-yamaha-yas-209"
